ncaa_stats_py/__init__.py
ncaa_stats_py/baseball.py
ncaa_stats_py/basketball.py
ncaa_stats_py/field_hockey.py
ncaa_stats_py/football.py
ncaa_stats_py/hockey.py
ncaa_stats_py/lacrosse.py
ncaa_stats_py/soccer.py
ncaa_stats_py/softball.py
ncaa_stats_py/utls.py
ncaa_stats_py/volleyball.py
ncaa_stats_py/helpers/football.py
ncaa_stats_py/helpers/volleyball.py
ncaa_stats_py-0.0.12.dist-info/licenses/LICENSE
ncaa_stats_py-0.0.12.dist-info/METADATA
ncaa_stats_py-0.0.12.dist-info/WHEEL
ncaa_stats_py-0.0.12.dist-info/top_level.txt
ncaa_stats_py-0.0.12.dist-info/RECORD
